colorharmonies/__init__.py
colorharmonies/colorharmonies.py
colorharmonies-1.0.5.dist-info/DESCRIPTION.rst
colorharmonies-1.0.5.dist-info/METADATA
colorharmonies-1.0.5.dist-info/RECORD
colorharmonies-1.0.5.dist-info/WHEEL
colorharmonies-1.0.5.dist-info/metadata.json
colorharmonies-1.0.5.dist-info/top_level.txt
